.bzrignore
COPYING
ChangeLog
INSTALL.txt
Makefile
README.txt
TODO.txt
crud.wpr
setup.cfg
setup.py
docs/Makefile
docs/index.txt
docs/install.txt
docs/modules.txt
docs/overview.txt
softwarefabrica/__init__.py
softwarefabrica.django.crud.egg-info/PKG-INFO
softwarefabrica.django.crud.egg-info/SOURCES.txt
softwarefabrica.django.crud.egg-info/dependency_links.txt
softwarefabrica.django.crud.egg-info/namespace_packages.txt
softwarefabrica.django.crud.egg-info/not-zip-safe
softwarefabrica.django.crud.egg-info/requires.txt
softwarefabrica.django.crud.egg-info/top_level.txt
softwarefabrica/django/__init__.py
softwarefabrica/django/crud/__init__.py
softwarefabrica/django/crud/bzrcachedrev.py
softwarefabrica/django/crud/crud.py
softwarefabrica/django/crud/finddata.py
softwarefabrica/django/crud/models.py
softwarefabrica/django/crud/version.py
softwarefabrica/django/crud/locale/it/LC_MESSAGES/django.mo
softwarefabrica/django/crud/locale/it/LC_MESSAGES/django.po