Metadata-Version: 1.0
Name: softwarefabrica.django.crud
Version: 1.0dev-BZR-r92-panta-elasticworld.org-20100503154915-oquvw7cswbvwnrvs
Summary: Advanced CRUD generic views library for SoftwareFabrica django projects
Home-page: http://cheeseshop.python.org/pypi/softwarefabrica.django.crud/
Author: Marco Pantaleoni
Author-email: m.pantaleoni@softwarefabrica.org
License: GNU GPL v2
Download-URL: http://pypi.python.org/packages/source/s/softwarefabrica.django.crud/softwarefabrica.django.crud-1.0dev-BZR-r92-panta-elasticworld.org-20100503154915-oquvw7cswbvwnrvs.tar.gz
Keywords: crud generic views django softwarefabrica
Platform: UNKNOWN
Classifier: Development Status :: 4 - Beta
Classifier: Framework :: Django
Classifier: Intended Audience :: Developers
Classifier: License :: OSI Approved :: GNU General Public License (GPL)
Classifier: Operating System :: OS Independent
Classifier: Programming Language :: Python :: 2.3
Classifier: Topic :: Software Development :: Libraries :: Python Modules
